[
    {
        "id": 1,
        "nombre": "DJI Mic Mini",
        "categoria": "accesorios",
        "compatibilidad": "universal",
        "tipo": "micrófono",
        "material": "otro",
        "peso": "10g",
        "dimensiones": "26.55 × 26.06 × 15.96 mm",
        "imagen": "dji-mic-mini.jpg",
        "recargable": "sí",
        "marca": "DJI",
        "precio": 334,
        "destacado": true
    },
    {
        "id": 2,
        "nombre": "Saramonic Blink 500 B2+",
        "categoria": "accesorios",
        "compatibilidad": "universal",
        "tipo": "micrófono",
        "material": "otro",
        "peso": "23g",
        "dimensiones": "45 × 31.6 × 13 mm",
        "imagen": "saramonic-blink-500-b2+.jpg",
        "recargable": "sí",
        "marca": "Saramonic",
        "precio": 435,
        "destacado": false
    },
    {
        "id": 3,
        "nombre": "BOYA Magic-02",
        "categoria": "accesorios",
        "compatibilidad": "universal",
        "tipo": "micrófono",
        "material": "otro",
        "peso": "7g",
        "dimensiones": "35 × 15.2 × 13 mm",
        "imagen": "boya-magic-02.jpg",
        "recargable": "no",
        "marca": "BOYA",
        "precio": 438,
        "destacado": false
    },
    {
        "id": 4,
        "nombre": "CAMBOFOTO Trípode",
        "categoria": "accesorios",
        "compatibilidad": "universal",
        "tipo": "trípode",
        "material": "aluminio",
        "peso": "3.3lb",
        "dimensiones": "4.7 x 4.9 x 17.3 in",
        "imagen": "cambofoto-tripode.jpg",
        "recargable": "no",
        "marca": "CAMBOFOTO",
        "precio": 100,
        "destacado": false
    },
    {
        "id": 5,
        "nombre": "NEEWER Trípode",
        "categoria": "accesorios",
        "compatibilidad": "universal",
        "tipo": "trípode",
        "material": "aluminio",
        "peso": "113.17oz",
        "dimensiones": "26.4 x 26.4 x 72.4 in",
        "imagen": "neewer-tripode.jpg",
        "recargable": "no",
        "marca": "NEEWER",
        "precio": 438,
        "destacado": false
    },
    {
        "id": 6,
        "nombre": "K&F CONCEPT Trípode",
        "categoria": "accesorios",
        "compatibilidad": "universal",
        "tipo": "trípode",
        "material": "aluminio",
        "peso": "4.45lb",
        "dimensiones": "22.6 x 5.2 x 5.2 in",
        "imagen": "k&f-concept-tripode.jpg",
        "recargable": "no",
        "marca": "K&F CONCEPT",
        "precio": 337,
        "destacado": false
    },
    {
        "id": 7,
        "nombre": "Peak Design Trípode",
        "categoria": "accesorios",
        "compatibilidad": "universal",
        "tipo": "trípode",
        "material": "fibra de carbono",
        "peso": "1.29kg",
        "dimensiones": "0.83 x 3.11 x 15.35 in",
        "imagen": "peak-design-tripode.jpg",
        "recargable": "no",
        "marca": "Peak Design",
        "precio": 2022,
        "destacado": false
    },
    {
        "id": 8,
        "nombre": "ULANZI VL49 RGB",
        "categoria": "accesorios",
        "compatibilidad": "universal",
        "tipo": "luces de cámara",
        "material": "otro",
        "peso": "100g",
        "dimensiones": "2.59 x 1.18 x 3.14 in",
        "imagen": "ulanzi-vl49-rgb.jpg",
        "recargable": "sí",
        "marca": "ULANZI",
        "precio": 64,
        "destacado": false
    },
    {
        "id": 9,
        "nombre": "Moman PC8 LED",
        "categoria": "accesorios",
        "compatibilidad": "universal",
        "tipo": "luces de cámara",
        "material": "otro",
        "peso": "125g",
        "dimensiones": "4.53 x 2.68 x 0.63 in",
        "imagen": "moman-pc8-led.jpg",
        "recargable": "sí",
        "marca": "Moman",
        "precio": 108,
        "destacado": false
    },
    {
        "id": 10,
        "nombre": "MOSISO Mochila",
        "categoria": "accesorios",
        "compatibilidad": "universal",
        "tipo": "mochila",
        "material": "otro",
        "peso": "3.2lb",
        "dimensiones": "17.32 x 11.8 x 7.5 in",
        "imagen": "mosiso-mochila.jpg",
        "recargable": "no",
        "marca": "MOSISO",
        "precio": 192,
        "destacado": false
    },
    {
        "id": 11,
        "nombre": "FUJIFILM X-M5",
        "categoria": "camaras-digitales",
        "sensor": "CMOS 23.5 x 15.6 mm",
        "resolucion": "26.1MP",
        "iso_max": 12800,
        "estabilizacion": "sí",
        "grabacion": "6.2K",
        "marca": "FUJIFILM",
        "peso": "2.1lb",
        "montura": "Fujifilm X",
        "imagen": "fujifilm-x-m5.jpg",
        "precio": 4210,
        "destacado": true
    },
    {
        "id": 12,
        "nombre": "Canon EOS Rebel T7",
        "categoria": "camaras-digitales",
        "sensor": "CMOS APS-C",
        "resolucion": "24.1MP",
        "iso_max": 6400,
        "estabilizacion": "sí",
        "grabacion": "1080p",
        "marca": "Canon",
        "peso": "1.04lb",
        "montura": "Canon EF",
        "imagen": "canon-eos-rebel-t7.jpg",
        "precio": 1950,
        "destacado": false
    },
    {
        "id": 13,
        "nombre": "Nikon D7500",
        "categoria": "camaras-digitales",
        "sensor": "CMOS APS-C",
        "resolucion": "20.9MP",
        "iso_max": 51200,
        "estabilizacion": "sí",
        "grabacion": "4K",
        "marca": "Nikon",
        "peso": "1.66lb",
        "montura": "Nikon DX",
        "imagen": "nikon-d7500.jpg",
        "precio": 3697,
        "destacado": false
    },
    {
        "id": 14,
        "nombre": "Pentax KF",
        "categoria": "camaras-digitales",
        "sensor": "CMOS APS-C",
        "resolucion": "24MP",
        "iso_max": 102400,
        "estabilizacion": "sí",
        "grabacion": "1080p",
        "marca": "Pentax",
        "peso": "1.22kg",
        "montura": "Pentax KAF",
        "imagen": "pentax-kf.jpg",
        "precio": 2180,
        "destacado": false
    },
    {
        "id": 15,
        "nombre": "Canon EOS 5D Mark IV",
        "categoria": "camaras-digitales",
        "sensor": "CMOS Full Frame",
        "resolucion": "30.4MP",
        "iso_max": 32000,
        "estabilizacion": "sí",
        "grabacion": "4K",
        "marca": "Canon",
        "peso": "1.24kg",
        "montura": "Canon EF",
        "imagen": "canon-eos-5d-mark-iv.jpg",
        "precio": 5675,
        "destacado": true
    },
    {
        "id": 16,
        "nombre": "FUJIFILM X100VI",
        "categoria": "camaras-digitales",
        "sensor": "CMOS APS-H",
        "resolucion": "40.2MP",
        "iso_max": 12800,
        "estabilizacion": "sí",
        "grabacion": "4320p",
        "marca": "FUJIFILM",
        "peso": "1.98lb",
        "montura": "Fujifilm X",
        "imagen": "fujifilm-x100vi.jpg",
        "precio": 7917,
        "destacado": false
    },
    {
        "id": 17,
        "nombre": "Sony Alpha 7 IV",
        "categoria": "camaras-digitales",
        "sensor": "CMOS Full Frame",
        "resolucion": "33MP",
        "iso_max": 51200,
        "estabilizacion": "sí",
        "grabacion": "4320p",
        "marca": "Sony",
        "peso": "955g",
        "montura": "Sony E",
        "imagen": "sony-alpha-7-iv.jpg",
        "precio": 7408,
        "destacado": true
    },
    {
        "id": 18,
        "nombre": "Sony A6400",
        "categoria": "camaras-digitales",
        "sensor": "CMOS APS-C",
        "resolucion": "25MP",
        "iso_max": 32000,
        "estabilizacion": "no",
        "grabacion": "4K",
        "marca": "Sony",
        "peso": "10.3oz",
        "montura": "Sony Sin espejo",
        "imagen": "sony-a6400.jpg",
        "precio": 3195,
        "destacado": false
    },
    {
        "id": 19,
        "nombre": "Olympus OM-1 Mark II",
        "categoria": "camaras-digitales",
        "sensor": "MOS BSI apilado",
        "resolucion": "20MP",
        "iso_max": 25600,
        "estabilizacion": "sí",
        "grabacion": "4K",
        "marca": "OM SYSTEM",
        "peso": "599g",
        "montura": "Micro Cuatro Tercios",
        "imagen": "olympus-om-1-mark-ii.jpg",
        "precio": 6740,
        "destacado": false
    },
    {
        "id": 20,
        "nombre": "Nikon D850",
        "categoria": "camaras-digitales",
        "sensor": "CMOS 35.9 x 23.9 mm",
        "resolucion": "45.7MP",
        "iso_max": 25600,
        "estabilizacion": "sí",
        "grabacion": "4K",
        "marca": "Nikon",
        "peso": "2.02lb",
        "montura": "Nikon F",
        "imagen": "nikon-d850.jpg",
        "precio": 6730,
        "destacado": false
    },
    {
        "id": 21,
        "nombre": "Sony ILME-FX6",
        "categoria": "camaras-video",
        "tipo": "cinema",
        "resolucion": "4K",
        "fps": "120p",
        "montura": "Sony E",
        "almacenamiento": "Cfexpress Tipo A/SDXC",
        "marca": "Sony",
        "peso": "2lb",
        "imagen": "sony-ilme-fx6.jpg",
        "precio": 24600,
        "destacado": true
    },
    {
        "id": 22,
        "nombre": "Canon EOS C80",
        "categoria": "camaras-video",
        "tipo": "cinema",
        "resolucion": "6K",
        "fps": "60p",
        "montura": "Canon RF",
        "almacenamiento": "SD/SDHC/SDXC",
        "marca": "Canon",
        "peso": "6.54lb",
        "imagen": "canon-eos-c80.jpg",
        "precio": 16382,
        "destacado": false
    },
    {
        "id": 23,
        "nombre": "Blackmagic 6K Pro",
        "categoria": "camaras-video",
        "tipo": "cinema",
        "resolucion": "6K",
        "fps": "60p",
        "montura": "Canon EF",
        "almacenamiento": "SD",
        "marca": "Blackmagic Design",
        "peso": "4.6lb",
        "imagen": "blackmagic-6k-pro.jpg",
        "precio": 10175,
        "destacado": false
    },
    {
        "id": 24,
        "nombre": "OBSBOT Tiny 2 Lite",
        "categoria": "camaras-video",
        "tipo": "broadcast",
        "resolucion": "4K",
        "fps": "60p",
        "montura": "Propia",
        "almacenamiento": "N/A",
        "marca": "OBSBOT",
        "peso": "91.4g",
        "imagen": "obsbot-tiny-2-lite.jpg",
        "precio": 536,
        "destacado": false
    },
    {
        "id": 25,
        "nombre": "DJI Osmo Pocket 3",
        "categoria": "camaras-video",
        "tipo": "broadcast",
        "resolucion": "4K",
        "fps": "60p",
        "montura": "Propia", 
        "almacenamiento": "microSD",
        "marca": "DJI",
        "peso": "179g",
        "imagen": "dji-osmo-pocket-3.jpg",
        "precio": 1818,
        "destacado": false
    },
    {
        "id": 26,
        "nombre": "Xtra Muse",
        "categoria": "camaras-video",
        "tipo": "broadcast",
        "resolucion": "4K",
        "fps": "60p",
        "montura": "Propia",
        "almacenamiento": "microSD",
        "marca": "Xtra Edge",
        "peso": "180g",
        "imagen": "xtra-muse.jpg",
        "precio": 1513,
        "destacado": false
    },
    {
        "id": 27,
        "nombre": "KODAK PIXPRO FZ55-BK",
        "categoria": "camaras-video",
        "tipo": "compacta",
        "resolucion": "1080p",
        "fps": "30p",
        "montura": "Nikon F",
        "almacenamiento": "SD/SDHC/SDXC",
        "marca": "KODAK",
        "peso": "106g",
        "imagen": "kodak-pixpro-fz55-bk.jpg",
        "precio": 472,
        "destacado": false
    },
    {
        "id": 28,
        "nombre": "Panasonic LUMIX ZS99",
        "categoria": "camaras-video",
        "tipo": "compacta",
        "resolucion": "4K",
        "fps": "30p",
        "montura": "Leica L",
        "almacenamiento": "SD/SDHC/SDXC",
        "marca": "Panasonic",
        "peso": "322g",
        "imagen": "panasonic-lumix-zs99.jpg",
        "precio": 2353,
        "destacado": false
    },
    {
        "id": 29,
        "nombre": "DJI Mini 4K",
        "categoria": "drones",
        "resolucion": "4K",
        "autonomia": 93,
        "sensor": "CMOS",
        "estabilizacion": "sí",
        "peso": "<249g",
        "marca": "DJI",
        "imagen": "dji-mini-4k.jpg",
        "precio": 1008,
        "destacado": false
    },
    {
        "id": 30,
        "nombre": "TL16LCD GPS 4K",
        "categoria": "drones",
        "resolucion": "4K",
        "autonomia": 20,
        "sensor": "CMOS",
        "estabilizacion": "sí",
        "peso": "<249g",
        "marca": "Tolatoyus",
        "imagen": "tl16lcd-gps-4k.jpg",
        "precio": 674,
        "destacado": false
    },
    {
        "id": 31,
        "nombre": "N11 Pro GPS",
        "categoria": "drones",
        "resolucion": "4K",
        "autonomia": 90,
        "sensor": "CMOS",
        "estabilizacion": "sí",
        "peso": "<249g",
        "marca": "NAFYRE",
        "imagen": "n11-pro-gps.jpg",
        "precio": 1410,
        "destacado": false
    },
    {
        "id": 32,
        "nombre": "DJI Flip",
        "categoria": "drones",
        "resolucion": "4K",
        "autonomia": 31,
        "sensor": "CMOS",
        "estabilizacion": "sí",
        "peso": "<249g",
        "marca": "DJI",
        "imagen": "dji-flip.jpg",
        "precio": 2520,
        "destacado": false
    },
    {
        "id": 33,
        "nombre": "DJI Neo",
        "categoria": "drones",
        "resolucion": "4K",
        "autonomia": 18,
        "sensor": "CMOS",
        "estabilizacion": "sí",
        "peso": "135g",
        "marca": "DJI",
        "imagen": "dji-neo.jpg",
        "precio": 660,
        "destacado": false
    },
    {
        "id": 34,
        "nombre": "DJI Mini 3",
        "categoria": "drones",
        "resolucion": "4K",
        "autonomia": 114,
        "sensor": "CMOS",
        "estabilizacion": "sí",
        "peso": "<249g",
        "marca": "DJI",
        "imagen": "dji-mini-3.jpg",
        "precio": 2423,
        "destacado": true
    },
    {
        "id": 35,
        "nombre": "FEELWORLD P6X",
        "categoria": "ecrans",
        "tamano": "5.5\"",
        "resolucion_monitor": "4K",
        "brillo": 1000,
        "relacion": "9:16",
        "entradas": "HDMI",
        "marca": "FEELWORLD",
        "imagen": "feelworld-p6x.jpg",
        "precio": 572,
        "destacado": false
    },
    {
        "id": 36,
        "nombre": "VILTROX DC-X3",
        "categoria": "ecrans",
        "tamano": "6\"",
        "resolucion_monitor": "4K",
        "brillo": 2000,
        "relacion": "16:09",
        "entradas": "HDMI/3G-SDI",
        "marca": "VILTROX",
        "imagen": "viltrox-dc-x3.jpg",
        "precio": 903,
        "destacado": false
    },
    {
        "id": 37,
        "nombre": "osee T7",
        "categoria": "ecrans",
        "tamano": "7\"",
        "resolucion_monitor": "FHD",
        "brillo": 3000,
        "relacion": "16:10",
        "entradas": "HDMI",
        "marca": "osee",
        "imagen": "osee-t7.jpg",
        "precio": 1102,
        "destacado": false
    },
    {
        "id": 38,
        "nombre": "osee Mega 15S",
        "categoria": "ecrans",
        "tamano": "15\"",
        "resolucion_monitor": "2K",
        "brillo": 1500,
        "relacion": "16:10",
        "entradas": "HDMI/3G-SDI",
        "marca": "osee",
        "imagen": "osee-mega-15s.jpg",
        "precio": 3198,
        "destacado": false
    },
    {
        "id": 39,
        "nombre": "FEELWORLD LUT11S",
        "categoria": "ecrans",
        "tamano": "10\"",
        "resolucion_monitor": "FHD",
        "brillo": 2000,
        "relacion": "16:10",
        "entradas": "HDMI/3G-SDI",
        "marca": "FEELWORLD",
        "imagen": "feelworld-lut11s.jpg",
        "precio": 1179,
        "destacado": false
    },
    {
        "id": 40,
        "nombre": "VILTROX DC-A1",
        "categoria": "ecrans",
        "tamano": "7\"",
        "resolucion_monitor": "4K",
        "brillo": 2800,
        "relacion": "16:09",
        "entradas": "HDMI",
        "marca": "VILTROX",
        "imagen": "viltrox-dc-a1.jpg",
        "precio": 937,
        "destacado": false
    }
]
